sshame/__init__.py
sshame/__main__.py
sshame/db.py
sshame/main.py
sshame-0.7.dist-info/LICENSE
sshame-0.7.dist-info/METADATA
sshame-0.7.dist-info/WHEEL
sshame-0.7.dist-info/entry_points.txt
sshame-0.7.dist-info/namespace_packages.txt
sshame-0.7.dist-info/top_level.txt
sshame-0.7.dist-info/RECORD
