Metadata-Version: 2.1
Name: sshame
Version: 0.7
Summary: SSH public key brute force tool
Home-page: https://github.com/hynek.petrak/sshame
Author: Hynek Petrak
Author-email: hynek.petrak@gmail.com
License: UNKNOWN
Download-URL: https://github.com/hynek.petrak/sshame/tarball/master
Platform: Any
Classifier: Development Status :: 4 - Beta
Classifier: License :: OSI Approved :: MIT License
Classifier: Programming Language :: Python :: 3 :: Only
Classifier: Intended Audience :: Other Audience
Classifier: Environment :: Console
Classifier: Operating System :: OS Independent
Classifier: Topic :: Security
Requires-Dist: asyncssh (>=1.15.1)
Requires-Dist: cmd2 (>=0.9.15)
Requires-Dist: colorama
Requires-Dist: sqlalchemy
Requires-Dist: scapy
Requires-Dist: tabulate
Requires-Dist: pyyaml
Requires-Dist: pysubnettree
